pytest_mypy/__init__.py
pytest_mypy/py.typed
pytest_mypy-1.0.0.dist-info/LICENSE
pytest_mypy-1.0.0.dist-info/METADATA
pytest_mypy-1.0.0.dist-info/WHEEL
pytest_mypy-1.0.0.dist-info/entry_points.txt
pytest_mypy-1.0.0.dist-info/top_level.txt
pytest_mypy-1.0.0.dist-info/RECORD
