Metadata-Version: 2.1
Name: pytest-mypy
Version: 1.0.0
Summary: A Pytest Plugin for Mypy
Maintainer-email: David Tucker <david@tucker.name>
License: The MIT License (MIT)
Project-URL: homepage, https://github.com/realpython/pytest-mypy
Classifier: Development Status :: 5 - Production/Stable
Classifier: Framework :: Pytest
Classifier: Intended Audience :: Developers
Classifier: License :: OSI Approved :: MIT License
Classifier: Operating System :: OS Independent
Classifier: Programming Language :: Python
Classifier: Programming Language :: Python :: 3
Classifier: Programming Language :: Python :: 3.8
Classifier: Programming Language :: Python :: 3.9
Classifier: Programming Language :: Python :: 3.10
Classifier: Programming Language :: Python :: 3.11
Classifier: Programming Language :: Python :: 3.12
Classifier: Programming Language :: Python :: 3.13
Classifier: Programming Language :: Python :: Implementation :: CPython
Classifier: Topic :: Software Development :: Testing
Requires-Python: >=3.8
License-File: LICENSE
Requires-Dist: filelock >=3.0
Requires-Dist: mypy >=1.0
Requires-Dist: pytest >=7.0
